pyretechnics/__init__.py
pyretechnics/burn_cells.py
pyretechnics/conversion.py
pyretechnics/crown_fire.py
pyretechnics/eulerian_level_set.py
pyretechnics/fire_spread.py
pyretechnics/fuel_models.py
pyretechnics/load_landfire.py
pyretechnics/space_time_cube.py
pyretechnics/spot_fire.py
pyretechnics/surface_fire.py
pyretechnics/vector_utils.py
pyretechnics-2024.11.7.dist-info/METADATA
pyretechnics-2024.11.7.dist-info/WHEEL
pyretechnics-2024.11.7.dist-info/licenses/LICENSE
pyretechnics-2024.11.7.dist-info/RECORD
