Metadata-Version: 2.3
Name: pyretechnics
Version: 2024.11.7
Summary: A Python library for simulating fire behavior in a variety of ways.
Project-URL: Homepage, https://pyregence.github.io/pyretechnics/
Project-URL: Documentation, https://pyregence.github.io/pyretechnics/
Project-URL: Repository, https://github.com/pyregence/pyretechnics/
Project-URL: Issues, https://github.com/pyregence/pyretechnics/issues/
Project-URL: Changelog, https://github.com/pyregence/pyretechnics/blob/main/CHANGELOG.md
Author-email: "Gary W. Johnson, PhD" <gjohnson@sig-gis.com>, Valentin Waeselynck <vwaeselynck@sig-gis.com>, "Chris Lautenberger, PhD, PE" <chris@cloudfire.ai>
License: Eclipse Public License - v 2.0
License-File: LICENSE
Keywords: fire,fire behavior,fire spread,wildfire
Classifier: Development Status :: 4 - Beta
Classifier: License :: OSI Approved :: Eclipse Public License 2.0 (EPL-2.0)
Classifier: Natural Language :: English
Classifier: Operating System :: OS Independent
Classifier: Programming Language :: Python :: 3
Classifier: Topic :: Scientific/Engineering
Requires-Python: >=3.10
Requires-Dist: matplotlib
Requires-Dist: numpy
Requires-Dist: rasterio
Provides-Extra: dev
Requires-Dist: pytest; extra == 'dev'
Requires-Dist: twine; extra == 'dev'
